MANIFEST.in
README.md
setup.py
src/masonite/logging/ChannelFactory.py
src/masonite/logging/Logger.py
src/masonite/logging/__init__.py
src/masonite/logging/factory.py
src/masonite/logging/listeners.py
src/masonite/logging/channels/BaseChannel.py
src/masonite/logging/channels/DailyChannel.py
src/masonite/logging/channels/MultiBaseChannel.py
src/masonite/logging/channels/SingleChannel.py
src/masonite/logging/channels/SlackChannel.py
src/masonite/logging/channels/StackChannel.py
src/masonite/logging/channels/SyslogChannel.py
src/masonite/logging/channels/TerminalChannel.py
src/masonite/logging/channels/__init__.py
src/masonite/logging/configs/logging.py
src/masonite/logging/drivers/BaseDriver.py
src/masonite/logging/drivers/LogSingleDriver.py
src/masonite/logging/drivers/LogSlackDriver.py
src/masonite/logging/drivers/LogSyslogDriver.py
src/masonite/logging/drivers/LogTerminalDriver.py
src/masonite/logging/drivers/__init__.py
src/masonite/logging/managers/LoggingManager.py
src/masonite/logging/managers/__init__.py
src/masonite/logging/providers/LoggingProvider.py
src/masonite/logging/providers/__init__.py
src/masonite_logging.egg-info/PKG-INFO
src/masonite_logging.egg-info/SOURCES.txt
src/masonite_logging.egg-info/dependency_links.txt
src/masonite_logging.egg-info/requires.txt
src/masonite_logging.egg-info/top_level.txt